molimg/__init__.py
molimg/draw.py
molimg/excel.py
molimg/helpers.py
molimg-0.2.0.dist-info/LICENSE
molimg-0.2.0.dist-info/METADATA
molimg-0.2.0.dist-info/WHEEL
molimg-0.2.0.dist-info/RECORD
