Metadata-Version: 2.1
Name: molimg
Version: 0.2.0
Summary: 
Home-page: https://github.com/jdkern11/molimg.git
Author: jdkern11
Author-email: josephdanielkern@gmail.com
Requires-Python: >=3.10,<4.0
Classifier: Programming Language :: Python :: 3
Classifier: Programming Language :: Python :: 3.10
Classifier: Programming Language :: Python :: 3.11
Requires-Dist: pandas (>=1.5.3,<2.0.0)
Requires-Dist: rdkit (>=2022.9.4,<2023.0.0)
Requires-Dist: xlsxwriter (>=3.0.8,<4.0.0)
Project-URL: Repository, https://github.com/jdkern11/molimg.git
